cleverbot/__init__.py
cleverbot/__main__.py
cleverbot/base.py
cleverbot/cleverbot.py
cleverbot/errors.py
cleverbot/migrations.py
cleverbot/utils.py
cleverbot/async_/__init__.py
cleverbot/async_/cleverbot.py
cleverbot.py-2.5.0.dist-info/LICENSE.txt
cleverbot.py-2.5.0.dist-info/METADATA
cleverbot.py-2.5.0.dist-info/RECORD
cleverbot.py-2.5.0.dist-info/WHEEL
cleverbot.py-2.5.0.dist-info/top_level.txt
