Metadata-Version: 2.1
Name: cleverbot.py
Version: 2.5.0
Summary: A Cleverbot API wrapper for Python with asynchronous functionality.
Home-page: https://github.com/orlnub123/cleverbot.py
Author: orlnub123
License: MIT
Platform: UNKNOWN
Classifier: Development Status :: 5 - Production/Stable
Classifier: License :: OSI Approved :: MIT License
Classifier: Natural Language :: English
Classifier: Operating System :: OS Independent
Classifier: Intended Audience :: Developers
Classifier: Programming Language :: Python :: 2
Classifier: Programming Language :: Python :: 2.7
Classifier: Programming Language :: Python :: 3
Classifier: Programming Language :: Python :: 3.2
Classifier: Programming Language :: Python :: 3.3
Classifier: Programming Language :: Python :: 3.4
Classifier: Programming Language :: Python :: 3.5
Classifier: Programming Language :: Python :: 3.6
Classifier: Programming Language :: Python :: 3.7
Classifier: Topic :: Internet
Classifier: Topic :: Games/Entertainment
Classifier: Topic :: Software Development :: Libraries :: Python Modules
Classifier: Topic :: Utilities
Requires-Python: >=2.7, !=3.0.*, !=3.1.*
Provides-Extra: async
Requires-Dist: requests (>=1.0.0)
Provides-Extra: async
Requires-Dist: aiohttp (>=1.0.0); extra == 'async'
